frakkcomm/__init__.py
frakkcomm/ejjelifeny.py
frakkcomm/eszkoz.py
frakkcomm/frakkcomm.py
frakkcomm-1.0.1.dist-info/LICENSE
frakkcomm-1.0.1.dist-info/METADATA
frakkcomm-1.0.1.dist-info/WHEEL
frakkcomm-1.0.1.dist-info/top_level.txt
frakkcomm-1.0.1.dist-info/RECORD
