Metadata-Version: 2.1
Name: frakkcomm
Version: 1.0.1
Summary: Custom TCP communication system
Author: Zoltán Fraknói
Project-URL: Homepage, https://github.com/Vogete/frakkcomm
Classifier: Programming Language :: Python :: 3
Classifier: License :: OSI Approved :: MIT License
Classifier: Operating System :: OS Independent
Requires-Python: >=3.7
License-File: LICENSE
